{
  "65": [
    223,
    221,
    222,
    354,
    328,
    341,
    342,
    374,
    375,
    381,
    386,
    388
  ],
  "46": [
    339,
    229,
    372,
    377,
    381
  ],
  "38": [
    239,
    228,
    226,
    336,
    357,
    351,
    224,
    363,
    388
  ],
  "18": [
    318,
    333,
    322,
    313,
    320,
    290,
    316,
    347,
    298,
    314,
    248
  ],
  "59": [
    233,
    337,
    350,
    235,
    230,
    343,
    374
  ],
  "60": [
    353,
    338,
    335,
    352,
    344,
    380
  ],
  "71": [
    356,
    348,
    373,
    379
  ],
  "4": [
    220
  ],
  "2": [
    250,
    215,
    345
  ],
  "22": [
    263,
    291,
    308,
    297,
    246
  ],
  "15": [
    241
  ],
  "16": [
    243,
    362
  ],
  "21": [
    293,
    260,
    370
  ],
  "7": [
    227
  ],
  "1": [
    245,
    360,
    359,
    231,
    365,
    340
  ],
  "69": [
    361,
    382,
    383,
    384
  ],
  "8": [
    358,
    375,
    385
  ],
  "14": [
    240
  ],
  "64": [
    364
  ],
  "54": [
    372
  ],
  "76": [
    378
  ],
  "63": [
    380
  ],
  "45": [
    387
  ],
  "72": [
    388
  ],
  "85": [
    388
  ],
  "75": [
    388
  ]
}